[
    {
        "Company Name": "Rudy",
        "RSP Type": "Regukar/Exp",
        "Santa Elena Border ": "",
        "Corozal": "2:45",
        "Orange Walk": "4:00",
        "Burrell Boom Junction": "5:00",
        "Belize City": "",
        "Days of Operation": "MonSun"
    },
    {
        "Company Name": "elio",
        "RSP Type": "Regular",
        "Santa Elena Border ": "",
        "Corozal": "",
        "Orange Walk": "5:15",
        "Burrell Boom Junction": "6:15",
        "Belize City": "7:00",
        "Days of Operation": "MonSat"
    },
    {
        "Company Name": "Joel",
        "RSP Type": "Express",
        "Santa Elena Border ": "",
        "Corozal": "",
        "Orange Walk": "4:30",
        "Burrell Boom Junction": "",
        "Belize City": "6:00",
        "Days of Operation": "MonFri"
    },
    {
        "Company Name": "elioA",
        "RSP Type": "Regular",
        "Santa Elena Border ": "",
        "Corozal": "",
        "Orange Walk": "",
        "Burrell Boom Junction": "5:15",
        "Belize City": "6:00",
        "Days of Operation": "MonSun "
    },
    {
        "Company Name": "Valencia (Benque)",
        "RSP Type": "Regular/Exp",
        "Santa Elena Border ": "",
        "Corozal": "3:00",
        "Orange Walk": "4:15",
        "Burrell Boom Junction": "5:15",
        "Belize City": "",
        "Days of Operation": "MonSun"
    },
    {
        "Company Name": "Julio",
        "RSP Type": "Regular",
        "Santa Elena Border ": "",
        "Corozal": "3:00",
        "Orange Walk": "4:15",
        "Burrell Boom Junction": "5:15",
        "Belize City": "6:00",
        "Days of Operation": "MonSat"
    },
    {
        "Company Name": "Valencia",
        "RSP Type": "Regular",
        "Santa Elena Border ": "",
        "Corozal": "3:15",
        "Orange Walk": "4:15",
        "Burrell Boom Junction": "5:15",
        "Belize City": "",
        "Days of Operation": "Mon"
    },
    {
        "Company Name": "Valencia (Benque)",
        "RSP Type": "Regular/Exp",
        "Santa Elena Border ": "",
        "Corozal": "3:30",
        "Orange Walk": "4:45",
        "Burrell Boom Junction": "5:45",
        "Belize City": "",
        "Days of Operation": "MonSun"
    },
    {
        "Company Name": "Victor Cal",
        "RSP Type": "Regular",
        "Santa Elena Border ": "",
        "Corozal": "3:30",
        "Orange Walk": "4:45",
        "Burrell Boom Junction": "5:45",
        "Belize City": "6:30",
        "Days of Operation": "MonSun"
    },
    {
        "Company Name": "elio A",
        "RSP Type": "Regular",
        "Santa Elena Border ": "",
        "Corozal": "",
        "Orange Walk": "",
        "Burrell Boom Junction": "5:45",
        "Belize City": "6:30",
        "Days of Operation": "MonSat "
    },
    {
        "Company Name": "Joshua",
        "RSP Type": "Exp- from Douglas",
        "Santa Elena Border ": "",
        "Corozal": "",
        "Orange Walk": "5:00",
        "Burrell Boom Junction": "6:00",
        "Belize City": "6:30",
        "Days of Operation": "MonSat"
    },
    {
        "Company Name": "Albion",
        "RSP Type": "Express",
        "Santa Elena Border ": "",
        "Corozal": "",
        "Orange Walk": "5:15",
        "Burrell Boom Junction": "6:15",
        "Belize City": "6:45",
        "Days of Operation": "MonSat"
    },
    {
        "Company Name": "Leon",
        "RSP Type": "Express to Bmp",
        "Santa Elena Border ": "",
        "Corozal": "",
        "Orange Walk": "5:15",
        "Burrell Boom Junction": "6:15",
        "Belize City": "",
        "Days of Operation": "MonSun"
    },
    {
        "Company Name": "elio Tillett Jr.",
        "RSP Type": "Express",
        "Santa Elena Border ": "",
        "Corozal": "",
        "Orange Walk": "",
        "Burrell Boom Junction": "6:30",
        "Belize City": "7:00",
        "Days of Operation": "MonSun"
    },
    {
        "Company Name": "Ovences",
        "RSP Type": "Regular",
        "Santa Elena Border ": "",
        "Corozal": "",
        "Orange Walk": "5:45",
        "Burrell Boom Junction": "6:45",
        "Belize City": "7:30",
        "Days of Operation": "MonSat"
    },
    {
        "Company Name": "Cabrera's",
        "RSP Type": "Regular",
        "Santa Elena Border ": "",
        "Corozal": "4:00",
        "Orange Walk": "5:15",
        "Burrell Boom Junction": "6:15",
        "Belize City": "7:00",
        "Days of Operation": "MonSun"
    },
    {
        "Company Name": "Albion",
        "RSP Type": "Express",
        "Santa Elena Border ": "",
        "Corozal": "",
        "Orange Walk": "5:20",
        "Burrell Boom Junction": "6:20",
        "Belize City": "6:50",
        "Days of Operation": "MonFri"
    },
    {
        "Company Name": "Alfredo",
        "RSP Type": "Regular",
        "Santa Elena Border ": "",
        "Corozal": "",
        "Orange Walk": "5:25",
        "Burrell Boom Junction": "6:25",
        "Belize City": "7:10",
        "Days of Operation": "MonSat"
    },
    {
        "Company Name": "Chell's ",
        "RSP Type": "Express",
        "Santa Elena Border ": "",
        "Corozal": "",
        "Orange Walk": "5:30",
        "Burrell Boom Junction": "6:30",
        "Belize City": "7:00",
        "Days of Operation": "MonSat"
    },
    {
        "Company Name": "Rudy",
        "RSP Type": "Regular",
        "Santa Elena Border ": "4:00",
        "Corozal": "4:15",
        "Orange Walk": "5:30",
        "Burrell Boom Junction": "6:30",
        "Belize City": "7:15",
        "Days of Operation": "MonSun"
    },
    {
        "Company Name": "Ernesto",
        "RSP Type": "Regular",
        "Santa Elena Border ": "",
        "Corozal": "",
        "Orange Walk": "5:50",
        "Burrell Boom Junction": "6:50",
        "Belize City": "7:35",
        "Days of Operation": "MonSun"
    },
    {
        "Company Name": "Ernesto",
        "RSP Type": "Express",
        "Santa Elena Border ": "",
        "Corozal": "",
        "Orange Walk": "5:50",
        "Burrell Boom Junction": "6:50",
        "Belize City": "7:20",
        "Days of Operation": "MonSun"
    },
    {
        "Company Name": "Michael",
        "RSP Type": "Express",
        "Santa Elena Border ": "",
        "Corozal": "",
        "Orange Walk": "5:55",
        "Burrell Boom Junction": "6:55",
        "Belize City": "7:25",
        "Days of Operation": "MonFri"
    },
    {
        "Company Name": "Rene Tillett",
        "RSP Type": "Express",
        "Santa Elena Border ": "",
        "Corozal": "",
        "Orange Walk": "6:00",
        "Burrell Boom Junction": "7:00",
        "Belize City": "7:30",
        "Days of Operation": "MonSat"
    },
    {
        "Company Name": "Rene Tillett",
        "RSP Type": "Express",
        "Santa Elena Border ": "",
        "Corozal": "",
        "Orange Walk": "6:00",
        "Burrell Boom Junction": "7:00",
        "Belize City": "7:30",
        "Days of Operation": "MonSat"
    },
    {
        "Company Name": "Cecil",
        "RSP Type": "Workers Exp",
        "Santa Elena Border ": "",
        "Corozal": "",
        "Orange Walk": "6:00",
        "Burrell Boom Junction": "7:00",
        "Belize City": "7:30",
        "Days of Operation": "MonFri"
    },
    {
        "Company Name": "Valdemar ",
        "RSP Type": "Express",
        "Santa Elena Border ": "",
        "Corozal": "",
        "Orange Walk": "6:00",
        "Burrell Boom Junction": "7:00",
        "Belize City": "7:30",
        "Days of Operation": "MonSat"
    },
    {
        "Company Name": "Valdemar ",
        "RSP Type": "Express",
        "Santa Elena Border ": "",
        "Corozal": "",
        "Orange Walk": "6:00",
        "Burrell Boom Junction": "7:00",
        "Belize City": "7:30",
        "Days of Operation": "MonSun"
    },
    {
        "Company Name": "Valdemar ",
        "RSP Type": "Express",
        "Santa Elena Border ": "",
        "Corozal": "",
        "Orange Walk": "6:10",
        "Burrell Boom Junction": "7:10",
        "Belize City": "7:40",
        "Days of Operation": "MonSun"
    },
    {
        "Company Name": "Valdemar ",
        "RSP Type": "Express",
        "Santa Elena Border ": "",
        "Corozal": "",
        "Orange Walk": "6:15",
        "Burrell Boom Junction": "7:15",
        "Belize City": "7:45",
        "Days of Operation": "MonSat"
    },
    {
        "Company Name": "Rudy",
        "RSP Type": "Regular",
        "Santa Elena Border ": "4:30",
        "Corozal": "4:45",
        "Orange Walk": "6:15",
        "Burrell Boom Junction": "7:30",
        "Belize City": "8:00",
        "Days of Operation": "MonSun"
    },
    {
        "Company Name": "Rudy",
        "RSP Type": "Workers Exp.",
        "Santa Elena Border ": "",
        "Corozal": "5:00",
        "Orange Walk": "",
        "Burrell Boom Junction": "",
        "Belize City": "7:45",
        "Days of Operation": "MonFri"
    },
    {
        "Company Name": "Rudy",
        "RSP Type": "Workers Exp.",
        "Santa Elena Border ": "",
        "Corozal": "5:05",
        "Orange Walk": "",
        "Burrell Boom Junction": "",
        "Belize City": "7:35",
        "Days of Operation": "MonFri"
    },
    {
        "Company Name": "Rene",
        "RSP Type": "Express",
        "Santa Elena Border ": "",
        "Corozal": "",
        "Orange Walk": "6:20",
        "Burrell Boom Junction": "7:20",
        "Belize City": "7:50",
        "Days of Operation": "MonSat"
    },
    {
        "Company Name": "Rene",
        "RSP Type": "Express",
        "Santa Elena Border ": "",
        "Corozal": "",
        "Orange Walk": "6:25",
        "Burrell Boom Junction": "7:25",
        "Belize City": "7:55",
        "Days of Operation": "MonSat"
    },
    {
        "Company Name": "Rene",
        "RSP Type": "Express",
        "Santa Elena Border ": "",
        "Corozal": "",
        "Orange Walk": "6:30",
        "Burrell Boom Junction": "7:30",
        "Belize City": "8:00",
        "Days of Operation": "MonSat"
    },
    {
        "Company Name": "Valdemar ",
        "RSP Type": "Express",
        "Santa Elena Border ": "",
        "Corozal": "",
        "Orange Walk": "6:30",
        "Burrell Boom Junction": "7:30",
        "Belize City": "8:00",
        "Days of Operation": "MonSat"
    },
    {
        "Company Name": "Rudy",
        "RSP Type": "Regular",
        "Santa Elena Border ": "5:00",
        "Corozal": "5:15",
        "Orange Walk": "6:45",
        "Burrell Boom Junction": "7:45",
        "Belize City": "8:30",
        "Days of Operation": "MonSun"
    },
    {
        "Company Name": "Valdemar ",
        "RSP Type": "Regular",
        "Santa Elena Border ": "",
        "Corozal": "",
        "Orange Walk": "6:45",
        "Burrell Boom Junction": "7:45",
        "Belize City": "8:30",
        "Days of Operation": "MonSat"
    },
    {
        "Company Name": "Rene",
        "RSP Type": "Express",
        "Santa Elena Border ": "",
        "Corozal": "",
        "Orange Walk": "6:45",
        "Burrell Boom Junction": "7:45",
        "Belize City": "8:15",
        "Days of Operation": "MonSat"
    },
    {
        "Company Name": "Valencia ",
        "RSP Type": "Regular",
        "Santa Elena Border ": "5:15",
        "Corozal": "5:45",
        "Orange Walk": "7:00",
        "Burrell Boom Junction": "8:00",
        "Belize City": "8:45",
        "Days of Operation": "MonSun"
    },
    {
        "Company Name": "Omar  Tillett ",
        "RSP Type": "Express",
        "Santa Elena Border ": "",
        "Corozal": "",
        "Orange Walk": "7:00",
        "Burrell Boom Junction": "8:00",
        "Belize City": "8:30",
        "Days of Operation": "MonSat"
    },
    {
        "Company Name": "Valdemar ",
        "RSP Type": "Express",
        "Santa Elena Border ": "",
        "Corozal": "",
        "Orange Walk": "7:15",
        "Burrell Boom Junction": "8:15",
        "Belize City": "8:45",
        "Days of Operation": "MonSat"
    },
    {
        "Company Name": "Valencia ",
        "RSP Type": "Regular",
        "Santa Elena Border ": "5:45",
        "Corozal": "6:15",
        "Orange Walk": "7:30",
        "Burrell Boom Junction": "8:30",
        "Belize City": "9:15",
        "Days of Operation": "MonSat"
    },
    {
        "Company Name": "elio ",
        "RSP Type": "Regular ",
        "Santa Elena Border ": "",
        "Corozal": "",
        "Orange Walk": "7:30",
        "Burrell Boom Junction": "8:30",
        "Belize City": "9:15",
        "Days of Operation": "MonSat"
    },
    {
        "Company Name": "elio",
        "RSP Type": "Regular",
        "Santa Elena Border ": "6:15",
        "Corozal": "6:45",
        "Orange Walk": "8:00",
        "Burrell Boom Junction": "9:00",
        "Belize City": "9:45",
        "Days of Operation": "MonSun"
    },
    {
        "Company Name": "Ovences",
        "RSP Type": "Express",
        "Santa Elena Border ": "",
        "Corozal": "",
        "Orange Walk": "8:15",
        "Burrell Boom Junction": "9:15",
        "Belize City": "10:00",
        "Days of Operation": "MonSat"
    },
    {
        "Company Name": "elio Tillett Jr.",
        "RSP Type": "Regular",
        "Santa Elena Border ": "6:45",
        "Corozal": "7:15",
        "Orange Walk": "8:30",
        "Burrell Boom Junction": "9:30",
        "Belize City": "10:15",
        "Days of Operation": "MonSun"
    },
    {
        "Company Name": "elio",
        "RSP Type": "Regular",
        "Santa Elena Border ": "7:15",
        "Corozal": "7:45",
        "Orange Walk": "9:00",
        "Burrell Boom Junction": "10:00",
        "Belize City": "10:45",
        "Days of Operation": "MonSun"
    },
    {
        "Company Name": "Rene Tillett",
        "RSP Type": "Regular",
        "Santa Elena Border ": "8:00",
        "Corozal": "8:30",
        "Orange Walk": "9:45",
        "Burrell Boom Junction": "10:45",
        "Belize City": "11:30",
        "Days of Operation": "MonSun"
    },
    {
        "Company Name": "Rudy",
        "RSP Type": "Regular",
        "Santa Elena Border ": "",
        "Corozal": "9:30",
        "Orange Walk": "10:45",
        "Burrell Boom Junction": "11:45",
        "Belize City": "12:30",
        "Days of Operation": "MonSun"
    },
    {
        "Company Name": "Wilmer",
        "RSP Type": "Shuttle",
        "Santa Elena Border ": "9:30",
        "Corozal": "10:00",
        "Orange Walk": "",
        "Burrell Boom Junction": "",
        "Belize City": "",
        "Days of Operation": "MonSat"
    },
    {
        "Company Name": "Suel Alilla (Albions)",
        "RSP Type": "Regular",
        "Santa Elena Border ": "10:00",
        "Corozal": "10:30",
        "Orange Walk": "11:45",
        "Burrell Boom Junction": "12:45",
        "Belize City": "13:30",
        "Days of Operation": "MonSun"
    },
    {
        "Company Name": "Omar",
        "RSP Type": "Regular",
        "Santa Elena Border ": "11:00",
        "Corozal": "11:30",
        "Orange Walk": "12:45",
        "Burrell Boom Junction": "13:45",
        "Belize City": "14:30",
        "Days of Operation": "MonSun"
    },
    {
        "Company Name": "Silva",
        "RSP Type": "Express to BVO",
        "Santa Elena Border ": "11:15",
        "Corozal": "11:45",
        "Orange Walk": "13:00",
        "Burrell Boom Junction": "13:45",
        "Belize City": "14:15",
        "Days of Operation": "MonSun"
    },
    {
        "Company Name": "Omar",
        "RSP Type": "Regular",
        "Santa Elena Border ": "11:30",
        "Corozal": "12:00",
        "Orange Walk": "13:15",
        "Burrell Boom Junction": "14:15",
        "Belize City": "15:00",
        "Days of Operation": "MonSun "
    },
    {
        "Company Name": "Alfonso",
        "RSP Type": "Regular",
        "Santa Elena Border ": "12:00",
        "Corozal": "12:30",
        "Orange Walk": "14:00",
        "Burrell Boom Junction": "15:00",
        "Belize City": "15:45",
        "Days of Operation": "MonSat"
    },
    {
        "Company Name": "Chell's ",
        "RSP Type": "O/W only",
        "Santa Elena Border ": "12:15",
        "Corozal": "12:45",
        "Orange Walk": "",
        "Burrell Boom Junction": "",
        "Belize City": "",
        "Days of Operation": "MonSun"
    },
    {
        "Company Name": "Omar",
        "RSP Type": "Regular",
        "Santa Elena Border ": "12:45",
        "Corozal": "13:15",
        "Orange Walk": "",
        "Burrell Boom Junction": "",
        "Belize City": "",
        "Days of Operation": "MonSat"
    },
    {
        "Company Name": " Omar",
        "RSP Type": "O/W Only ",
        "Santa Elena Border ": "13:00",
        "Corozal": "13:30",
        "Orange Walk": "",
        "Burrell Boom Junction": "",
        "Belize City": "",
        "Days of Operation": "MonSat"
    },
    {
        "Company Name": "Omar",
        "RSP Type": "Regular",
        "Santa Elena Border ": "13:15",
        "Corozal": "13:45",
        "Orange Walk": "15:00",
        "Burrell Boom Junction": "16:00",
        "Belize City": "16:45",
        "Days of Operation": "MonSun"
    },
    {
        "Company Name": "elio Tillett Jr.",
        "RSP Type": "Regular to ShipYard",
        "Santa Elena Border ": "13:30",
        "Corozal": "14:00",
        "Orange Walk": "",
        "Burrell Boom Junction": "",
        "Belize City": "",
        "Days of Operation": "MonSat "
    },
    {
        "Company Name": "Andrew",
        "RSP Type": "Regular",
        "Santa Elena Border ": "13:45",
        "Corozal": "14:15",
        "Orange Walk": "15:30",
        "Burrell Boom Junction": "16:30",
        "Belize City": "17:15",
        "Days of Operation": "MonSat"
    },
    {
        "Company Name": "Carlos Marinez",
        "RSP Type": "Regular",
        "Santa Elena Border ": "14:15",
        "Corozal": "14:45",
        "Orange Walk": "16:00",
        "Burrell Boom Junction": "17:00",
        "Belize City": "17:45",
        "Days of Operation": "MonSun"
    },
    {
        "Company Name": "Terrence",
        "RSP Type": "Regular",
        "Santa Elena Border ": "14:30",
        "Corozal": "15:00",
        "Orange Walk": "16:15",
        "Burrell Boom Junction": "17:15",
        "Belize City": "18:00",
        "Days of Operation": "Sun"
    },
    {
        "Company Name": "Suel",
        "RSP Type": "Regular",
        "Santa Elena Border ": "14:45",
        "Corozal": "15:15",
        "Orange Walk": "16:30",
        "Burrell Boom Junction": "17:30",
        "Belize City": "18:15",
        "Days of Operation": "MonSun"
    },
    {
        "Company Name": "Michael Frazer",
        "RSP Type": "O/W  (Reg)",
        "Santa Elena Border ": "15:00",
        "Corozal": "15:30",
        "Orange Walk": "",
        "Burrell Boom Junction": "",
        "Belize City": "",
        "Days of Operation": "MonSat"
    },
    {
        "Company Name": "Ovences",
        "RSP Type": "Regular",
        "Santa Elena Border ": "15:00",
        "Corozal": "15:30",
        "Orange Walk": "",
        "Burrell Boom Junction": "",
        "Belize City": "",
        "Days of Operation": "MonSun"
    },
    {
        "Company Name": "Silva",
        "RSP Type": "Express to BVO",
        "Santa Elena Border ": "15:15",
        "Corozal": "15:45",
        "Orange Walk": "17:00",
        "Burrell Boom Junction": "17:50",
        "Belize City": "18:20",
        "Days of Operation": "MonSun"
    },
    {
        "Company Name": "Joshua",
        "RSP Type": "Regular",
        "Santa Elena Border ": "15:30",
        "Corozal": "16:00",
        "Orange Walk": "17:15",
        "Burrell Boom Junction": "18:05",
        "Belize City": "18:50",
        "Days of Operation": "MonSun"
    },
    {
        "Company Name": "Albion",
        "RSP Type": "Regular",
        "Santa Elena Border ": "15:45",
        "Corozal": "16:15",
        "Orange Walk": "17:30",
        "Burrell Boom Junction": "18:30",
        "Belize City": "19:15",
        "Days of Operation": "MonSun"
    },
    {
        "Company Name": "BBOC ",
        "RSP Type": "Regular",
        "Santa Elena Border ": "16:15",
        "Corozal": "16:45",
        "Orange Walk": "18:00",
        "Burrell Boom Junction": "19:00",
        "Belize City": "19:45",
        "Days of Operation": "MonSun"
    },
    {
        "Company Name": "BBOC",
        "RSP Type": "Regular",
        "Santa Elena Border ": "16:45",
        "Corozal": "17:15",
        "Orange Walk": "18:30",
        "Burrell Boom Junction": "19:30",
        "Belize City": "20:15",
        "Days of Operation": "MonSun"
    },
    {
        "Company Name": "BBOC",
        "RSP Type": "Regular",
        "Santa Elena Border ": "17:15",
        "Corozal": "17:45",
        "Orange Walk": "19:00",
        "Burrell Boom Junction": "20:00",
        "Belize City": "20:45",
        "Days of Operation": "MonSun"
    },
    {
        "Company Name": "Carlos",
        "RSP Type": "Regular",
        "Santa Elena Border ": "17:30",
        "Corozal": "18:00",
        "Orange Walk": "",
        "Burrell Boom Junction": "",
        "Belize City": "",
        "Days of Operation": "Sun"
    },
    {
        "Company Name": "elio Tilltt Jr.",
        "RSP Type": "Express",
        "Santa Elena Border ": "18:00",
        "Corozal": "18:30",
        "Orange Walk": "",
        "Burrell Boom Junction": "",
        "Belize City": "",
        "Days of Operation": ""
    },
    {
        "Company Name": "BBOC",
        "RSP Type": "Regular",
        "Santa Elena Border ": "18:15",
        "Corozal": "18:45",
        "Orange Walk": "20:00",
        "Burrell Boom Junction": "21:00",
        "Belize City": "21:45",
        "Days of Operation": "MonSun"
    },
    {
        "Company Name": "elio Tillett Jr.B",
        "RSP Type": "Regular to San Felipe",
        "Santa Elena Border ": "18:30",
        "Corozal": "19:00",
        "Orange Walk": "20:15",
        "Burrell Boom Junction": "",
        "Belize City": "",
        "Days of Operation": "MonSat"
    },
    {
        "Company Name": "BBOC",
        "RSP Type": "Regular",
        "Santa Elena Border ": "18:45",
        "Corozal": "19:15",
        "Orange Walk": "20:30",
        "Burrell Boom Junction": "21:30",
        "Belize City": "22:15",
        "Days of Operation": "MonSun"
    }
]
